scratchclickerapi/__init__.py
scratchclickerwebsiteapi-0.0.2.dist-info/METADATA
scratchclickerwebsiteapi-0.0.2.dist-info/WHEEL
scratchclickerwebsiteapi-0.0.2.dist-info/top_level.txt
scratchclickerwebsiteapi-0.0.2.dist-info/RECORD
